[
  {"timestamp": 0, "my_score": [0, 0], "their_score": [0, 0], "serving": "them"},
  {"timestamp": 5.383, "my_score": [0, 15], "their_score": [0, 0], "serving": "them"},
  {"timestamp": 16.583, "my_score": [0, 15], "their_score": [0, 15], "serving": "them"},
  {"timestamp": 25.733, "my_score": [0, 15], "their_score": [0, 30], "serving": "them"},
  {"timestamp": 38.317, "my_score": [0, 15], "their_score": [0, 40], "serving": "them"},
  {"timestamp": 43.355, "my_score": [0, 30], "their_score": [0, 40], "serving": "them"},
  {"timestamp": 55.372, "my_score": [0, 40], "their_score": [0, 40], "serving": "them"},
  {"timestamp": 55.372, "my_score": [0, 40], "their_score": [0, 40], "serving": "them"},
  {"timestamp": "1:14.588", "my_score": [0, 40], "their_score": [0, "AD"], "serving": "them"},
  {"timestamp": "1:21.188", "my_score": [0, 40], "their_score": [0, 40], "serving": "them"},
  {"timestamp": "1:24.538", "my_score": [0, "AD"], "their_score": [0, 40], "serving": "them"},
  {"timestamp": "1:29.438", "my_score": [1, 0], "their_score": [0, 0], "serving": "me"},
  {"timestamp": "1:32.805", "my_score": [1, 0], "their_score": [0, 15], "serving": "me"},
  {"timestamp": "1:53.155", "my_score": [1, 15], "their_score": [0, 30], "serving": "me"},
  {"timestamp": "2:28.622", "my_score": [1, 15], "their_score": [0, 40], "serving": "me"},
  {"timestamp": "2:31.455", "my_score": [1, 0], "their_score": [1, 0], "serving": "them"},
  {"timestamp": "2:36.238", "my_score": [1, 0], "their_score": [1, 15], "serving": "them"},
  {"timestamp": "2:44.172", "my_score": [1, 0], "their_score": [1, 30], "serving": "them"},
  {"timestamp": "2:55.972", "my_score": [1, 0], "their_score": [1, 40], "serving": "them"},
  {"timestamp": "3:00.287", "my_score": [1, 0], "their_score": [2, 0], "serving": "me"},
  {"timestamp": "3:08.037", "my_score": [1, 0], "their_score": [2, 15], "serving": "me"},
  {"timestamp": "3:12.503", "my_score": [1, 15], "their_score": [2, 15], "serving": "me"},
  {"timestamp": "3:23.737", "my_score": [1, 30], "their_score": [2, 15], "serving": "me"},
  {"timestamp": "3:28.537", "my_score": [1, 30], "their_score": [2, 30], "serving": "me"},
  {"timestamp": "3:31.420", "my_score": [1, 30], "their_score": [2, 40], "serving": "me"},
  {"timestamp": "3:34.287", "my_score": [1, 0], "their_score": [3, 0], "serving": "them"},
  {"timestamp": "3:39.920", "my_score": [1, 15], "their_score": [3, 0], "serving": "them"},
  {"timestamp": "3:58.453", "my_score": [1, 15], "their_score": [3, 15], "serving": "them"},
  {"timestamp": "4:15.820", "my_score": [1, 15], "their_score": [3, 30], "serving": "them"},
  {"timestamp": "4:28.537", "my_score": [1, 15], "their_score": [3, 40], "serving": "them"},
  {"timestamp": "4:33.620", "my_score": [1, 0], "their_score": [4, 0], "serving": "me"},
  {"timestamp": "4:52.537", "my_score": [1, 15], "their_score": [4, 0], "serving": "me"},
  {"timestamp": "5:01.503", "my_score": [1, 15], "their_score": [4, 15], "serving": "me"},
  {"timestamp": "5:11.353", "my_score": [1, 15], "their_score": [4, 30], "serving": "me"},
  {"timestamp": "5:29.587", "my_score": [1, 15], "their_score": [4, 40], "serving": "me"},
  {"timestamp": "5:37.620", "my_score": [1, 30], "their_score": [4, 40], "serving": "me"},
  {"timestamp": "5:40.520", "my_score": [1, 0], "their_score": [5, 0], "serving": "them"},
  {"timestamp": "5:45.637", "my_score": [1, 0], "their_score": [5, 15], "serving": "them"},
  {"timestamp": "5:52.353", "my_score": [1, 15], "their_score": [5, 15], "serving": "them"},
  {"timestamp": "6:01.237", "my_score": [1, 15], "their_score": [5, 30], "serving": "them"},
  {"timestamp": "6:16.920", "my_score": [1, 30], "their_score": [5, 30], "serving": "them"},
  {"timestamp": "6:33.387", "my_score": [1, 30], "their_score": [5, 40], "serving": "them"},
  {"timestamp": "6:43.687", "my_score": [1, 40], "their_score": [5, 40], "serving": "them"},
  {"timestamp": "6:49.237", "my_score": [1, 40], "their_score": [5, "AD"], "serving": "them"},
  {"timestamp": "6:54.270", "my_score": [1, 40], "their_score": [5, 40], "serving": "them"},
  {"timestamp": "6:59.570", "my_score": [1, 40], "their_score": [5, "AD"], "serving": "them"},
  {"timestamp": "7:03.720", "my_score": [1, 0, 0], "their_score": [6, 0, 0], "serving": "me"},
  {"timestamp": "7:10.270", "my_score": [1, 0, 0], "their_score": [6, 0, 15], "serving": "me"},
  {"timestamp": "7:26.070", "my_score": [1, 0, 0], "their_score": [6, 0, 40], "serving": "me"},
  {"timestamp": "7:32.037", "my_score": [1, 0, 0], "their_score": [6, 1, 0], "serving": "them"},
  {"timestamp": "7:40.220", "my_score": [1, 0, 15], "their_score": [6, 1, 0], "serving": "them"},
  {"timestamp": "8:00.870", "my_score": [1, 0, 15], "their_score": [6, 1, 15], "serving": "them"},
  {"timestamp": "8:13.037", "my_score": [1, 0, 15], "their_score": [6, 1, 30], "serving": "them"},
  {"timestamp": "8:32.887", "my_score": [1, 0, 15], "their_score": [6, 1, 40], "serving": "them"},
  {"timestamp": "8:37.737", "my_score": [1, 0, 0], "their_score": [6, 2, 0], "serving": "me"},
  {"timestamp": "8:58.137", "my_score": [1, 0, 0], "their_score": [6, 2, 15], "serving": "me"},
  {"timestamp": "9:09.220", "my_score": [1, 0, 15], "their_score": [6, 2, 15], "serving": "me"},
  {"timestamp": "9:20.470", "my_score": [1, 0, 30], "their_score": [6, 2, 15], "serving": "me"},
  {"timestamp": "9:40.037", "my_score": [1, 0, 30], "their_score": [6, 2, 30], "serving": "me"},
  {"timestamp": "10:08.770", "my_score": [1, 0, 40], "their_score": [6, 2, 30], "serving": "me"},
  {"timestamp": "10:13.753", "my_score": [1, 0, 40], "their_score": [6, 2, 40], "serving": "me"},
  {"timestamp": "10:18.020", "my_score": [1, 0, "AD"], "their_score": [6, 2, 40], "serving": "me"},
  {"timestamp": "10:31.170", "my_score": [1, 0, 40], "their_score": [6, 2, 40], "serving": "me"},
  {"timestamp": "10:37.537", "my_score": [1, 0, 40], "their_score": [6, 2, "AD"], "serving": "me"},
  {"timestamp": "10:53.737", "my_score": [1, 0, 0], "their_score": [6, 3, 0], "serving": "them"},
  {"timestamp": "11:04.537", "my_score": [1, 0, 0], "their_score": [6, 3, 15], "serving": "them"},
  {"timestamp": "11:13.970", "my_score": [1, 0, 15], "their_score": [6, 3, 15], "serving": "them"},
  {"timestamp": "11:19.637", "my_score": [1, 0, 30], "their_score": [6, 3, 15], "serving": "them"},
  {"timestamp": "11:33.237", "my_score": [1, 0, 30], "their_score": [6, 3, 30], "serving": "them"},
  {"timestamp": "12:08.003", "my_score": [1, 0, 30], "their_score": [6, 3, 40], "serving": "them"},
  {"timestamp": "12:15.820", "my_score": [1, 0, 40], "their_score": [6, 3, 40], "serving": "them"},
  {"timestamp": "12:31.720", "my_score": [1, 0, "AD"], "their_score": [6, 3, 40], "serving": "them"},
  {"timestamp": "12:38.370", "my_score": [1, 0, 40], "their_score": [6, 3, 40], "serving": "them"},
  {"timestamp": "12:48.187", "my_score": [1, 0, 40], "their_score": [6, 3, "AD"], "serving": "them"},
  {"timestamp": "12:53.437", "my_score": [1, 0, 0], "their_score": [6, 4, 0], "serving": "me"},
  {"timestamp": "13:03.887", "my_score": [1, 0, 15], "their_score": [6, 4, 0], "serving": "me"},
  {"timestamp": "13:08.837", "my_score": [1, 0, 30], "their_score": [6, 4, 0], "serving": "me"},
  {"timestamp": "13:16.503", "my_score": [1, 0, 30], "their_score": [6, 4, 15], "serving": "me"},
  {"timestamp": "13:36.753", "my_score": [1, 0, 40], "their_score": [6, 4, 15], "serving": "me"},
  {"timestamp": "13:48.003", "my_score": [1, 1, 0], "their_score": [6, 4, 0], "serving": "them"},
  {"timestamp": "14:05.870", "my_score": [1, 1, 15], "their_score": [6, 4, 0], "serving": "them"},
  {"timestamp": "14:31.153", "my_score": [1, 1, 15], "their_score": [6, 4, 15], "serving": "them"},
  {"timestamp": "14:42.003", "my_score": [1, 1, 15], "their_score": [6, 4, 30], "serving": "them"},
  {"timestamp": "14:50.253", "my_score": [1, 1, 15], "their_score": [6, 4, 40], "serving": "them"},
  {"timestamp": "14:53.270", "my_score": [1, 1, 0], "their_score": [6, 5, 0], "serving": "me"},
  {"timestamp": "14:58.120", "my_score": [1, 1, 15], "their_score": [6, 5, 0], "serving": "me"},
  {"timestamp": "15:13.387", "my_score": [1, 1, 15], "their_score": [6, 5, 15], "serving": "me"},
  {"timestamp": "15:16.237", "my_score": [1, 1, 30], "their_score": [6, 5, 30], "serving": "me"},
  {"timestamp": "15:19.137", "my_score": [1, 1, 30], "their_score": [6, 5, 40], "serving": "me"}
]